fleet_sdk/__init__.py
fleet_sdk/adapters/__init__.py
fleet_sdk/adapters/base_adapter.py
fleet_sdk/adapters/fastapi_adapter.py
fleet_sdk/adapters/flask_adapter.py
fleet_sdk/adapters/quart_adapter.py
fleet_sdk/base.py
fleet_sdk/fastapi.py
fleet_sdk/flask.py
fleet_sdk/quart.py
fleet_sdk-0.5.5.1.dist-info/METADATA
fleet_sdk-0.5.5.1.dist-info/WHEEL
fleet_sdk-0.5.5.1.dist-info/RECORD
